octo_drf/__init__.py
octo_drf/logging.py
octo_drf/settings.py
octo_drf/site_urls.py
octo_drf/apps/__init__.py
octo_drf/apps/auth/__init__.py
octo_drf/apps/auth/admin.py
octo_drf/apps/auth/handlers.py
octo_drf/apps/auth/models.py
octo_drf/apps/auth/serializers.py
octo_drf/apps/auth/urls.py
octo_drf/apps/auth/views.py
octo_drf/apps/base/__init__.py
octo_drf/apps/base/admin.py
octo_drf/apps/base/catalog_models.py
octo_drf/apps/base/core_template_tags.py
octo_drf/apps/base/generic.py
octo_drf/apps/base/mixins.py
octo_drf/apps/base/models.py
octo_drf/apps/base/serializers.py
octo_drf/apps/base/views.py
octo_drf/apps/base_forms/__init__.py
octo_drf/apps/base_forms/admin.py
octo_drf/apps/base_forms/apps.py
octo_drf/apps/base_forms/models.py
octo_drf/apps/base_forms/serializers.py
octo_drf/apps/base_forms/urls.py
octo_drf/apps/base_forms/views.py
octo_drf/apps/base_forms/migrations/0001_initial.py
octo_drf/apps/base_forms/migrations/__init__.py
octo_drf/apps/base_users/__init__.py
octo_drf/apps/base_users/forms.py
octo_drf/apps/base_users/models.py
octo_drf/apps/config/__init__.py
octo_drf/apps/config/admin.py
octo_drf/apps/config/decorators.py
octo_drf/apps/config/models.py
octo_drf/apps/filters/__init__.py
octo_drf/apps/filters/filters.py
octo_drf/apps/filters/mixins.py
octo_drf/apps/generic_image/__init__.py
octo_drf/apps/generic_image/admin.py
octo_drf/apps/generic_image/apps.py
octo_drf/apps/generic_image/fields.py
octo_drf/apps/generic_image/forms.py
octo_drf/apps/generic_image/mixin.py
octo_drf/apps/generic_image/models.py
octo_drf/apps/generic_image/path.py
octo_drf/apps/generic_image/serializers.py
octo_drf/apps/generic_image/storage.py
octo_drf/apps/generic_image/urls.py
octo_drf/apps/generic_image/views.py
octo_drf/apps/generic_image/migrations/__init__.py
octo_drf/apps/mailer/__init__.py
octo_drf/apps/mailer/admin.py
octo_drf/apps/mailer/api.py
octo_drf/apps/mailer/apps.py
octo_drf/apps/mailer/models.py
octo_drf-4.4.4.dist-info/DESCRIPTION.rst
octo_drf-4.4.4.dist-info/METADATA
octo_drf-4.4.4.dist-info/RECORD
octo_drf-4.4.4.dist-info/WHEEL
octo_drf-4.4.4.dist-info/metadata.json
octo_drf-4.4.4.dist-info/top_level.txt
