Metadata-Version: 2.0
Name: octo-drf
Version: 4.4.4
Summary: Django apps for OctoberWeb.
Home-page: https://gitlab.com/octoberweb/octo_drf_core
Author: Octoberweb
Author-email: test@octoberweb.ru
License: BSD License
Platform: UNKNOWN
Classifier: Environment :: Web Environment
Classifier: Framework :: Django
Classifier: Framework :: Django :: 2.0
Classifier: Intended Audience :: Developers
Classifier: License :: OSI Approved :: BSD License
Classifier: Operating System :: OS Independent
Classifier: Programming Language :: Python
Classifier: Programming Language :: Python :: 3.6
Classifier: Topic :: Internet :: WWW/HTTP
Classifier: Topic :: Internet :: WWW/HTTP :: Dynamic Content
Requires-Dist: Django (<3,>=2.0)
Requires-Dist: django-debug-toolbar (<2,>=1.7)
Requires-Dist: django-filter (<2,>=1.0.2)
Requires-Dist: django-mptt (<1,>=0.8.7)
Requires-Dist: postgres (<3,>=2.2.1)
Requires-Dist: sorl-thumbnail (>=12.3)
Requires-Dist: djangorestframework (>=3.6.2)
Requires-Dist: xhtml2pdf (==0.2b1)
Requires-Dist: html5lib (==1.0b10)
Requires-Dist: Pillow (<5,>=4.2.1)
Requires-Dist: pytz (>=2017.2)
Requires-Dist: coreapi (<3,>=2.3.0)
Requires-Dist: uWSGI (<3,>=2.0.15)
Requires-Dist: psycopg2-binary
Requires-Dist: requests (<3,>=2.13.0)
Requires-Dist: jinja2 (==2.8.1)
Requires-Dist: opbeat (<4,>=3.5.0)
Requires-Dist: django-rest-swagger (<3,>=2.1.2)
Requires-Dist: Fabric3 (>=1.13.0)
